[
  {
    "id": 1,
    "title": "第1周",
    "date": "2025-11-10 至 2025-11-16",
    "content": [
      "（1）Firebase 平台服务：Firebase Authentication可以方便的实现用户身份验证，Cloud Firestore可以实现用户数据云存储，通过安全规则数实现数据保护，最终效果是实现通过网页交互而非修改代码编辑网页内容",
      "实际使用体验：由于平台数据存储位置，在网页部署测试时发现实现网页数据交互需要科学上网，且免费数据存储额度较低，放弃",
      "（2）GitHub Pages 服务：GitHub Pages 是 GitHub 提供的一项用于托管静态网站的免费服务，它支持从仓库的特定分支自动构建和发布网站。",
      "（3）基础GIt仓库管理操作：用于管理个人网页的修改及发布。"
    ]
  },
  {
    "id": 2,
    "title": "第2周",
    "date": "2025-10-17 至 2025-10-23",
    "content": [
      "实现个人网站部署，用于记录及展示每周学习任务与目标",
      "本周及近期学习内容：",
      "（1）（长期目标）文献阅读：主要通过阅读文献梳理学习光谱定标相关知识，初步目标是了解光谱定标的实现全流程，重点掌握实验原理、计算公式以及影响误差的相关因素",
      "（2）（长期目标）复习遥原课程相关知识，学习高光谱遥感，定量遥感相关知识",
      "（3）（预计两周）复习数据结构与算法，提高编程能力"
    ]
  }

]



